.gitignore
CONTRIBUTING.md
LICENSE
PKG-INFO
README.md
pyproject.toml
.github/workflows/joss.yml
.github/workflows/publish.yml
.github/workflows/tests.yml
assets/cover.png
assets/cover_dark.png
configs/__init__.py
configs/shear.py
data/shear.py
data/shear/DES_shear-shear_a1.0_b0.5_data_vector
data/shear/covariance_cosmic_shear_PMEpaper.dat
data/shear/derivatives.dat
examples/shear.ipynb
examples/shear_nn.ipynb
examples/shear_optuna.ipynb
examples/shear_vmim.ipynb
examples/toy.ipynb
paper/paper.bib
paper/paper.md
paper/paper.pdf
paper/sbi_example.png
sbiax/__init__.py
sbiax/compression/__init__.py
sbiax/compression/linear.py
sbiax/compression/nn.py
sbiax/inference/__init__.py
sbiax/inference/nuts.py
sbiax/inference/nle/__init__.py
sbiax/meta/__init__.py
sbiax/meta/_optuna.py
sbiax/ndes/__init__.py
sbiax/ndes/cnf.py
sbiax/ndes/ensemble.py
sbiax/ndes/gmm.py
sbiax/ndes/maf.py
sbiax/ndes/scaler.py
sbiax/ndes/vmim.py
sbiax/train/__init__.py
sbiax/train/loader.py
sbiax/train/loss.py
sbiax/train/train.py
sbiax/utils/__init__.py
tests/requirements.txt
tests/test_fit_nn.py
tests/test_ndes.py
tests/test_npe_nle.py
tests/test_nuts.py
tests/test_toy_example.py
sbiax-0.0.57.dist-info/METADATA
sbiax-0.0.57.dist-info/WHEEL
sbiax-0.0.57.dist-info/licenses/LICENSE
sbiax-0.0.57.dist-info/RECORD
