Metadata-Version: 2.4
Name: sbiax
Version: 0.0.57
Summary: Fast, parallel and lightweight simulation-based inference in JAX.
Project-URL: repository, https://github.com/homerjed/sbiax
Author-email: Jed Homer <jedhmr@gmail.com>
License: MIT License
License-File: LICENSE
Keywords: bayesian-inference,deep-learning,generative-models,jax,likelihood-free-inference,machine-learning,simulation-based-inference
Classifier: Development Status :: 3 - Alpha
Classifier: Intended Audience :: Science/Research
Classifier: License :: OSI Approved :: MIT License
Classifier: Natural Language :: English
Classifier: Programming Language :: Python :: 3
Classifier: Topic :: Scientific/Engineering :: Artificial Intelligence
Requires-Python: >=3.10
Requires-Dist: beartype==0.19.0
Requires-Dist: blackjax==1.2.4
Requires-Dist: chainconsumer==1.1.2
Requires-Dist: cloudpickle==3.1.0
Requires-Dist: diffrax==0.6.0
Requires-Dist: einops==0.8.0
Requires-Dist: equinox==0.11.8
Requires-Dist: flowjax==16.0.0
Requires-Dist: jax-tqdm
Requires-Dist: jax==0.4.33
Requires-Dist: matplotlib==3.9.2
Requires-Dist: ml-collections==0.1.1
Requires-Dist: numpy==1.26.4
Requires-Dist: optax==0.2.3
Requires-Dist: optuna==4.0.0
Requires-Dist: plotly==5.24.1
Requires-Dist: tensorflow-probability==0.24.0
Requires-Dist: tqdm==4.66.5
